<DOMSymbolItem xmlns:xsi="http://www.w3.org/2001/XMLSchema-instance" xmlns="http://ns.adobe.com/xfl/2008/" name="Mc_circle_silver" itemID="5bf38c18-00002aaa" lastModified="1542688827" lastUniqueIdentifier="1">
  <timeline>
    <DOMTimeline name="Mc_circle_silver" currentFrame="89">
      <layers>
        <DOMLayer name="Layer_2" color="#9933CC" current="true" isSelected="true">
          <frames>
            <DOMFrame index="0" keyMode="9728">
              <elements/>
            </DOMFrame>
            <DOMFrame index="1" keyMode="9728">
              <Framescript language="JavaScript">
                <script><![CDATA[this.stop();]]></script>
              </Framescript>
              <elements/>
            </DOMFrame>
            <DOMFrame index="2" duration="87" name="start" labelType="name" keyMode="9728">
              <elements/>
            </DOMFrame>
            <DOMFrame index="89" keyMode="9728">
              <Framescript language="JavaScript">
                <script><![CDATA[this.gotoAndPla('start');]]></script>
              </Framescript>
              <elements/>
            </DOMFrame>
          </frames>
        </DOMLayer>
        <DOMLayer name="Layer_1" color="#00FFFF">
          <frames>
            <DOMFrame index="0" duration="2" keyMode="9728">
              <elements>
                <DOMSymbolInstance libraryItemName="Mc_silver">
                  <transformationPoint>
                    <Point x="95" y="107"/>
                  </transformationPoint>
                </DOMSymbolInstance>
              </elements>
            </DOMFrame>
            <DOMFrame index="2" duration="42" tweenType="motion" motionTweenRotate="clockwise" motionTweenRotateTimes="1" keyMode="17921">
              <elements>
                <DOMSymbolInstance libraryItemName="Mc_silver" centerPoint3DX="95" centerPoint3DY="107">
                  <transformationPoint>
                    <Point x="95" y="107"/>
                  </transformationPoint>
                </DOMSymbolInstance>
              </elements>
            </DOMFrame>
            <DOMFrame index="44" duration="45" tweenType="motion" motionTweenRotate="clockwise" motionTweenRotateTimes="1" keyMode="17921">
              <elements>
                <DOMSymbolInstance libraryItemName="Mc_silver" centerPoint3DX="95" centerPoint3DY="106.95">
                  <matrix>
                    <Matrix a="-0.986297607421875" b="0.161712646484375" c="-0.161712646484375" d="-0.986297607421875" tx="206" ty="197.15"/>
                  </matrix>
                  <transformationPoint>
                    <Point x="95" y="107.05"/>
                  </transformationPoint>
                  <color>
                    <Color brightness="0.71"/>
                  </color>
                </DOMSymbolInstance>
              </elements>
            </DOMFrame>
            <DOMFrame index="89" keyMode="9728">
              <elements>
                <DOMSymbolInstance libraryItemName="Mc_silver" centerPoint3DX="95" centerPoint3DY="107">
                  <transformationPoint>
                    <Point x="95" y="107"/>
                  </transformationPoint>
                </DOMSymbolInstance>
              </elements>
            </DOMFrame>
          </frames>
        </DOMLayer>
      </layers>
    </DOMTimeline>
  </timeline>
</DOMSymbolItem>